qtoggleserver/generichttp/__init__.py
qtoggleserver/generichttp/client.py
qtoggleserver/generichttp/ports.py
qtoggleserver_generic_http-1.3.0.dist-info/licenses/LICENSE.txt
qtoggleserver_generic_http-1.3.0.dist-info/METADATA
qtoggleserver_generic_http-1.3.0.dist-info/WHEEL
qtoggleserver_generic_http-1.3.0.dist-info/top_level.txt
qtoggleserver_generic_http-1.3.0.dist-info/RECORD
