Metadata-Version: 2.4
Name: qtoggleserver-generic-http
Version: 1.3.0
Summary: qToggleServer ports backed by configurable HTTP requests
Author-email: Calin Crisan <ccrisan@gmail.com>
License: Apache 2.0
Requires-Python: >=3.11
License-File: LICENSE.txt
Requires-Dist: aiohttp
Requires-Dist: jinja2
Requires-Dist: jsonpointer
Dynamic: license-file
